{"Exif":{"Lat":34.417227777777775,"Long":-112.15705833333334,"Date":"2024-02-13T17:10:58-07:00","Tags":{"DateTimeOriginal|time.Time":"2024-02-13T17:10:58-07:00","FocalLength":1.9500000476837158,"ImageUniqueID":"78019e425975ed130000000000000000","InteroperabilityIFDPointer|int":"454","InteroperabilityIndex":"R98","Make":"Google","Model":"Pixel 7 Pro","Orientation|int":"1","PixelXDimension|int":"4080","PixelYDimension|int":"3072","Software":"Picasa","SubjectDistance":4294967295,"YCbCrSubSampling":[2,2]}}}
